meow/__init__.py
meow/__main__.py
meow/config.py
meow/local-setup.py
meow/main.py
meow/commands/__init__.py
meow/commands/githandler.py
meow/core/__init__.py
meow/core/executor.py
meow/core/pipeline.py
meow/utils/__init__.py
meow/utils/gitutils.py
meow/utils/helpers.py
meow/utils/loaders.py
meow/utils/loggers.py
meower-1.2.1.dist-info/licenses/LICENSE
meower-1.2.1.dist-info/METADATA
meower-1.2.1.dist-info/WHEEL
meower-1.2.1.dist-info/entry_points.txt
meower-1.2.1.dist-info/top_level.txt
meower-1.2.1.dist-info/RECORD
