Metadata-Version: 2.4
Name: meower
Version: 1.2.1
Summary: a friendly git wrapper
Author: ellipticobj
Author-email: ellipticobj <luna@hackclub.app>
Classifier: Programming Language :: Python :: 3
Classifier: Topic :: Software Development :: Version Control :: Git
Requires-Python: >=3.12
License-File: LICENSE
Dynamic: author
Dynamic: license-file
Dynamic: requires-python
